MANIFEST.in
README.md
setup.cfg
setup.py
version.txt
bin/deepspeed
bin/deepspeed.pt
bin/ds
bin/ds_elastic
bin/ds_report
bin/ds_ssh
csrc/adagrad/cpu_adagrad.cpp
csrc/adam/cpu_adam.cpp
csrc/adam/fused_adam_frontend.cpp
csrc/adam/multi_tensor_adam.cu
csrc/adam/multi_tensor_apply.cuh
csrc/aio/common/deepspeed_aio_common.cpp
csrc/aio/common/deepspeed_aio_common.h
csrc/aio/common/deepspeed_aio_types.cpp
csrc/aio/common/deepspeed_aio_types.h
csrc/aio/common/deepspeed_aio_utils.cpp
csrc/aio/common/deepspeed_aio_utils.h
csrc/aio/py_lib/deepspeed_aio_thread.cpp
csrc/aio/py_lib/deepspeed_aio_thread.h
csrc/aio/py_lib/deepspeed_py_aio.cpp
csrc/aio/py_lib/deepspeed_py_aio.h
csrc/aio/py_lib/deepspeed_py_aio_handle.cpp
csrc/aio/py_lib/deepspeed_py_aio_handle.h
csrc/aio/py_lib/deepspeed_py_copy.cpp
csrc/aio/py_lib/deepspeed_py_copy.h
csrc/aio/py_lib/py_ds_aio.cpp
csrc/common/custom_cuda_kernel.cu
csrc/includes/StopWatch.h
csrc/includes/Timer.h
csrc/includes/compat.h
csrc/includes/context.h
csrc/includes/cpu_adagrad.h
csrc/includes/cpu_adam.h
csrc/includes/cublas_wrappers.h
csrc/includes/custom_cuda_layers.h
csrc/includes/dropout.h
csrc/includes/ds_transformer_cuda.h
csrc/includes/feed_forward.h
csrc/includes/gelu.h
csrc/includes/gemm_test.h
csrc/includes/general_kernels.h
csrc/includes/normalize_layer.h
csrc/includes/quantizer.h
csrc/includes/simd.h
csrc/includes/softmax.h
csrc/includes/strided_batch_gemm.h
csrc/includes/type_shim.h
csrc/lamb/fused_lamb_cuda.cpp
csrc/lamb/fused_lamb_cuda_kernel.cu
csrc/quantization/pt_binding.cpp
csrc/quantization/quantizer.cu
csrc/sparse_attention/utils.cpp
csrc/transformer/cublas_wrappers.cu
csrc/transformer/dropout_kernels.cu
csrc/transformer/ds_transformer_cuda.cpp
csrc/transformer/gelu_kernels.cu
csrc/transformer/general_kernels.cu
csrc/transformer/normalize_kernels.cu
csrc/transformer/softmax_kernels.cu
csrc/transformer/transform_kernels.cu
csrc/transformer/inference/csrc/apply_rotary_pos_emb.cu
csrc/transformer/inference/csrc/dequantize.cu
deepspeed_moee.egg-info/PKG-INFO
deepspeed_moee.egg-info/SOURCES.txt
deepspeed_moee.egg-info/dependency_links.txt
deepspeed_moee.egg-info/entry_points.txt
deepspeed_moee.egg-info/requires.txt
deepspeed_moee.egg-info/top_level.txt
