Metadata-Version: 2.1
Name: deepspeed-moee
Version: 0.12
Summary: DeepSpeed library
Home-page: http://deepspeed.ai
Author: Joel Jang
Author-email: wkddydpf@gmail.com
License: MIT
Project-URL: Documentation, https://deepspeed.readthedocs.io
Project-URL: Source, https://github.com/joeljang/DeepSpeed
Platform: UNKNOWN
Classifier: Programming Language :: Python :: 3.6
Classifier: Programming Language :: Python :: 3.7
Classifier: Programming Language :: Python :: 3.8
Classifier: Programming Language :: Python :: 3.9
Provides-Extra: 1bit
Provides-Extra: 1bit_mpi
Provides-Extra: readthedocs
Provides-Extra: dev
Provides-Extra: autotuning
Provides-Extra: autotuning_ml
Provides-Extra: sparse_attn
Provides-Extra: all
